config_params/__init__.py
config_params/constants.py
trim_rag/__init__.py
trim_rag/components/__init__.py
trim_rag/components/pinecone/__init__.py
trim_rag/components/pinecone/pinecone_setting.py
trim_rag/components/qdrant_db/__init__.py
trim_rag/components/qdrant_db/qdrant_setting.py
trim_rag/components/qdrant_db/vector_db.py
trim_rag/config/__init__.py
trim_rag/config/arguments_config.py
trim_rag/config/manager_config.py
trim_rag/data/__init__.py
trim_rag/data/audio/__init__.py
trim_rag/data/audio/audio_ingestion.py
trim_rag/data/images/__init__.py
trim_rag/data/images/checked_image.py
trim_rag/data/images/image_ingestion.py
trim_rag/data/text/__init__.py
trim_rag/data/text/file_ingestion.py
trim_rag/embedding/__init__.py
trim_rag/embedding/crossAttention.py
trim_rag/embedding/multimodal_embedding.py
trim_rag/embedding/sharedSpace.py
trim_rag/embedding/audio/__init__.py
trim_rag/embedding/audio/embed_audio.py
trim_rag/embedding/image/__init__.py
trim_rag/embedding/image/embed_image.py
trim_rag/embedding/text/__init__.py
trim_rag/embedding/text/embed_text.py
trim_rag/exception/__init__.py
trim_rag/exception/exception.py
trim_rag/generation/__init__.py
trim_rag/generation/customRunnable.py
trim_rag/generation/multimodal_generation.py
trim_rag/generation/post_processing.py
trim_rag/generation/prompt_flows.py
trim_rag/inference/__init__.py
trim_rag/inference/data_preparation.py
trim_rag/inference/embed_infer.py
trim_rag/inference/extract_inputIfer.py
trim_rag/inference/inference.py
trim_rag/logger/__init__.py
trim_rag/logger/logger_init.py
trim_rag/logger/logger_setting.py
trim_rag/models/__init__.py
trim_rag/models/audio_model.py
trim_rag/models/custom_audioModel.py
trim_rag/models/custom_imageModel.py
trim_rag/models/custom_textModel.py
trim_rag/models/image_model.py
trim_rag/models/multi_models.py
trim_rag/models/text_model.py
trim_rag/pipeline/__init__.py
trim_rag/pipeline/data_embedding.py
trim_rag/pipeline/data_ingestion.py
trim_rag/pipeline/data_processing.py
trimodal_rag-0.0.1.dist-info/LICENSE
trimodal_rag-0.0.1.dist-info/METADATA
trimodal_rag-0.0.1.dist-info/WHEEL
trimodal_rag-0.0.1.dist-info/top_level.txt
trimodal_rag-0.0.1.dist-info/RECORD
