Metadata-Version: 2.1
Name: trimodal-rag
Version: 0.0.1
Summary: A python package for applying TriModal Retrieval-Augmented Generation (RAG) system.
Home-page: https://github.com/tph-kds/TriModalRAG_System
Author: tph-kds
Author-email: tranphihung8383@gmail.com
License: MIT License
Project-URL: Bug Tracker, https://github.com/tph-kds/TriModalRAG_System/issues
Classifier: Environment :: GPU :: NVIDIA CUDA :: 11
Classifier: Environment :: GPU :: NVIDIA CUDA :: 11.8
Classifier: Intended Audience :: Developers
Classifier: Intended Audience :: Education
Classifier: Intended Audience :: Science/Research
Classifier: License :: OSI Approved :: MIT License
Classifier: Programming Language :: Python :: 3.9
Classifier: Programming Language :: Python :: 3.10
Classifier: Operating System :: OS Independent
Classifier: Topic :: Scientific/Engineering
Classifier: Topic :: Scientific/Engineering :: Artificial Intelligence
Classifier: Topic :: Scientific/Engineering :: Mathematics
Classifier: Topic :: Software Development
Classifier: Topic :: Software Development :: Libraries
Classifier: Topic :: Software Development :: Libraries :: Python Modules
Requires-Python: >=3.9
License-File: LICENSE
Requires-Dist: transformers
Requires-Dist: pandas
Requires-Dist: numpy
Requires-Dist: torch
Requires-Dist: huggingface-hub
Requires-Dist: langchain
Provides-Extra: testing
Requires-Dist: pytest>=7.1.3; extra == "testing"
Requires-Dist: pytest-cov>=3.0; extra == "testing"
Requires-Dist: mypy>=0.971; extra == "testing"
Requires-Dist: flake8>=5.0.4; extra == "testing"
Requires-Dist: tox>=3.25.1; extra == "testing"
Requires-Dist: black>=22.8.0; extra == "testing"
